map2poster/__init__.py
map2poster/__main__.py
map2poster/cli.py
map2poster/core.py
map2poster/font_management.py
map2poster/main.py
map2poster/fonts/Roboto-Bold.ttf
map2poster/fonts/Roboto-Light.ttf
map2poster/fonts/Roboto-Regular.ttf
map2poster/themes/autumn.json
map2poster/themes/blueprint.json
map2poster/themes/contrast_zones.json
map2poster/themes/copper_patina.json
map2poster/themes/emerald.json
map2poster/themes/forest.json
map2poster/themes/gradient_roads.json
map2poster/themes/japanese_ink.json
map2poster/themes/midnight_blue.json
map2poster/themes/monochrome_blue.json
map2poster/themes/neon_cyberpunk.json
map2poster/themes/noir.json
map2poster/themes/ocean.json
map2poster/themes/pastel_dream.json
map2poster/themes/sunset.json
map2poster/themes/terracotta.json
map2poster/themes/warm_beige.json
map2poster-0.2.4.dist-info/METADATA
map2poster-0.2.4.dist-info/WHEEL
map2poster-0.2.4.dist-info/entry_points.txt
map2poster-0.2.4.dist-info/top_level.txt
map2poster-0.2.4.dist-info/RECORD
