Metadata-Version: 2.4
Name: map2poster
Version: 0.2.4
Summary: Generate beautiful, minimalist map posters for any city in the world.
Author-email: Anton Vice <a1996nton@gmail.com>
Keywords: map,poster,osm,openstreetmap,art,visualization
Requires-Python: >=3.11
Requires-Dist: certifi
Requires-Dist: charset-normalizer
Requires-Dist: contourpy
Requires-Dist: cycler
Requires-Dist: fonttools
Requires-Dist: geographiclib
Requires-Dist: geopandas
Requires-Dist: geopy
Requires-Dist: idna
Requires-Dist: kiwisolver
Requires-Dist: lat-lon-parser
Requires-Dist: matplotlib
Requires-Dist: networkx
Requires-Dist: numpy
Requires-Dist: osmnx
Requires-Dist: packaging
Requires-Dist: pandas
Requires-Dist: pillow
Requires-Dist: pyogrio
Requires-Dist: pyparsing
Requires-Dist: pyproj
Requires-Dist: python-dateutil
Requires-Dist: pytz
Requires-Dist: requests
Requires-Dist: scipy
Requires-Dist: shapely
Requires-Dist: six
Requires-Dist: tqdm
Requires-Dist: tzdata
Requires-Dist: urllib3
